{
	"configurations" : 
	[
		{
			"directories" : 
			[
				{
					"build" : ".",
					"jsonFile" : "directory-.-Debug-f5ebdc15457944623624.json",
					"minimumCMakeVersion" : 
					{
						"string" : "3.21"
					},
					"projectIndex" : 0,
					"source" : ".",
					"targetIndexes" : 
					[
						0
					]
				}
			],
			"name" : "Debug",
			"projects" : 
			[
				{
					"directoryIndexes" : 
					[
						0
					],
					"name" : "makentoshe_arduino_pid_test",
					"targetIndexes" : 
					[
						0
					]
				}
			],
			"targets" : 
			[
				{
					"directoryIndex" : 0,
					"id" : "makentoshe_arduino_pid_test::@6890427a1f51a3e7e1df",
					"jsonFile" : "target-makentoshe_arduino_pid_test-Debug-7108c45967ba45b6fed0.json",
					"name" : "makentoshe_arduino_pid_test",
					"projectIndex" : 0
				}
			]
		}
	],
	"kind" : "codemodel",
	"paths" : 
	{
		"build" : "/cygdrive/p/project/makentoshe-arduino-pid-test/cmake-build-debug",
		"source" : "/cygdrive/p/project/makentoshe-arduino-pid-test"
	},
	"version" : 
	{
		"major" : 2,
		"minor" : 3
	}
}
